imod_coupler/__init__.py
imod_coupler/__main__.py
imod_coupler/config.py
imod_coupler/parser.py
imod_coupler/utils.py
imod_coupler/drivers/__init__.py
imod_coupler/drivers/driver.py
imod_coupler/drivers/metamod/__init__.py
imod_coupler/drivers/metamod/config.py
imod_coupler/drivers/metamod/metamod.py
imod_coupler-0.11.0.dist-info/LICENSE
imod_coupler-0.11.0.dist-info/METADATA
imod_coupler-0.11.0.dist-info/WHEEL
imod_coupler-0.11.0.dist-info/entry_points.txt
imod_coupler-0.11.0.dist-info/top_level.txt
imod_coupler-0.11.0.dist-info/RECORD
