Metadata-Version: 2.1
Name: imod-coupler
Version: 0.11.0
Summary: iMOD Coupler can be used to couple hydrological kernels
Home-page: https://github.com/Deltares/imod_coupler
Download-URL: https://pypi.org/project/imod_coupler/
Author: Julian Hofer, Martijn Russcher, Robert Leander, Joeri van Engelen
Author-email: Julian.Hofer@deltares.nl, Martijn.Russcher@deltares.nl, Robert.Leander@deltares.nl, Joeri.vanEngelen@deltares.nl
License: MIT
Platform: Windows
Classifier: Intended Audience :: Science/Research
Classifier: Topic :: Scientific/Engineering :: Hydrology
Requires-Python: >=3.8
License-File: LICENSE
Requires-Dist: numpy
Requires-Dist: scipy
Requires-Dist: xmipy
Requires-Dist: tomli
Requires-Dist: tomli-w
Requires-Dist: pydantic
Requires-Dist: loguru
Provides-Extra: check-packages
Requires-Dist: build ; extra == 'check-packages'
Requires-Dist: twine ; extra == 'check-packages'
Provides-Extra: docs
Requires-Dist: sphinx ; extra == 'docs'
Requires-Dist: pydata-sphinx-theme ; extra == 'docs'
Provides-Extra: lint
Requires-Dist: mypy ; extra == 'lint'
Requires-Dist: black ; extra == 'lint'
Requires-Dist: isort ; extra == 'lint'
Provides-Extra: tests
Requires-Dist: pytest ; extra == 'tests'
Requires-Dist: pytest-xdist ; extra == 'tests'
Requires-Dist: pytest-cases ; extra == 'tests'
Requires-Dist: pytest-dotenv ; extra == 'tests'
